pyrepec/__init__.py
pyrepec/models.py
pyrepec/repec.py
pyrepec-0.2.1.dist-info/LICENSE
pyrepec-0.2.1.dist-info/METADATA
pyrepec-0.2.1.dist-info/WHEEL
pyrepec-0.2.1.dist-info/RECORD
